{ "questions": [{
    "content": "What is the best game to buy?",
    "author": "Bob Smith",
    "note": "Wanting to know about games in general"
  }, {
    "content": "Where is the Space Needle?",
    "author": "Mary Smith",
    "note": "Is it in the USA?"
  }, {
    "content": "What is the best coffee to drink?",
    "author": "Joe Shoe",
    "note": "I'm not sure where to go for coffee."
  }],
  "answers": [{
    "author": "Nancy Razor",
    "content": "The Space Needle is in Seattle"
  }, {
    "author": "Nancy Razor",
    "content": "the best coffee to drink is in your living room."
  }]
}
